{
    "config":{
            "points_per_day":"4",
            "week_days":"5"
        },
    "classes":[
            { "code":"001", "name":"ALG", "points":"4", "teacher":"Alex" },
            { "code":"003", "name":"MAT", "points":"2", "teacher":"Alex" },
            { "code":"004", "name":"PSI", "points":"2", "teacher":"Alex" },
            { "code":"005", "name":"PSI", "points":"2", "teacher":"Alex" },
            { "code":"006", "name":"PSI", "points":"2", "teacher":"Alex" },
            { "code":"007", "name":"PSI", "points":"3", "teacher":"Alex" },
            { "code":"008", "name":"PSI", "points":"1", "teacher":"Alex" },
            { "code":"009", "name":"PSI", "points":"4", "teacher":"Alex" },
            { "code":"002", "name":"ENG", "points":"4", "teacher":"FHC" }
        ]
}
